{
  "name": "asterisk",
  "codepoint": "ea7f",
  "title": "asterisk",
  "svg": "<svg xmlns=\"http://www.w3.org/2000/svg\" viewBox=\"0 0 24 24\">\r\n    <g>\r\n        <path fill=\"none\" d=\"M0 0h24v24H0z\"/>\r\n        <path d=\"M13 3v7.267l6.294-3.633 1 1.732-6.293 3.633 6.293 3.635-1 1.732L13 13.732V21h-2v-7.268l-6.294 3.634-1-1.732L9.999 12 3.706 8.366l1-1.732L11 10.267V3z\"/>\r\n    </g>\r\n</svg>\r\n",
  "aliases": [],
  "tags": [
    {
      "title": "Editor",
      "titleZh": "编辑器",
      "count": 71,
      "name": "editor"
    }
  ],
  "dir": "editor",
  "style": "regular",
  "author": "Remix Design Studio",
  "version": "2.3.0",
  "zhs": [
    "*",
    "星号",
    "注释",
    "详细信息",
    "参考",
    "星级",
    "雪花",
    "米字",
    "米子健"
  ],
  "description": "星号，表示重点标注，电话暂停键，数学乘号，密码输入。",
  "comments": []
}