{
  "name": "layout-3-fill",
  "codepoint": "ee1f",
  "title": "layout 3 fill",
  "svg": "<svg xmlns=\"http://www.w3.org/2000/svg\" viewBox=\"0 0 24 24\">\r\n    <g>\r\n        <path fill=\"none\" d=\"M0 0h24v24H0z\"/>\r\n        <path d=\"M8 10v11H4a1 1 0 0 1-1-1V10h5zm13 0v10a1 1 0 0 1-1 1H10V10h11zm-1-7a1 1 0 0 1 1 1v4H3V4a1 1 0 0 1 1-1h16z\"/>\r\n    </g>\r\n</svg>\r\n",
  "aliases": [
    "collage",
    "fill"
  ],
  "tags": [
    {
      "title": "Design",
      "titleZh": "设计",
      "count": 80,
      "name": "design"
    }
  ],
  "dir": "design",
  "style": "fill",
  "author": "Remix Design Studio",
  "version": "2.3.0",
  "zhs": [
    "布局",
    "拼贴画"
  ],
  "description": "",
  "comments": []
}