{
  "name": "creative-commons-fill",
  "codepoint": "ebd5",
  "title": "creative commons fill",
  "svg": "<svg xmlns=\"http://www.w3.org/2000/svg\" viewBox=\"0 0 24 24\">\r\n    <g>\r\n        <path fill=\"none\" d=\"M0 0h24v24H0z\"/>\r\n        <path d=\"M12 2c5.523 0 10 4.477 10 10s-4.477 10-10 10S2 17.523 2 12 6.477 2 12 2zM9 8c-2.208 0-4 1.792-4 4a4.001 4.001 0 0 0 6.669 2.979l.159-.151-1.414-1.414a2 2 0 1 1-.125-2.943l.126.116 1.414-1.414A3.988 3.988 0 0 0 9 8zm7 0c-2.208 0-4 1.792-4 4a4.001 4.001 0 0 0 6.669 2.979l.159-.151-1.414-1.414a2 2 0 1 1-.125-2.943l.126.116 1.414-1.414A3.988 3.988 0 0 0 16 8z\"/>\r\n    </g>\r\n</svg>\r\n",
  "aliases": [
    "fill"
  ],
  "tags": [
    {
      "title": "Business",
      "titleZh": "商业",
      "count": 81,
      "name": "business"
    }
  ],
  "dir": "business",
  "style": "fill",
  "author": "Remix Design Studio",
  "version": "2.3.0",
  "zhs": [
    "知识共享"
  ],
  "description": "",
  "comments": []
}