{
  "name": "adjust",
  "codepoint": "f042",
  "title": "adjust",
  "svg": "<svg xmlns=\"http://www.w3.org/2000/svg\" viewBox=\"0 0 512 512\"><path d=\"M8 256c0 136.966 111.033 248 248 248s248-111.034 248-248S392.966 8 256 8 8 119.033 8 256zm248 184V72c101.705 0 184 82.311 184 184 0 101.705-82.311 184-184 184z\"/></svg>",
  "aliases": [
    "contrast",
    "dark",
    "light",
    "saturation"
  ],
  "tags": [
    {
      "title": "Design",
      "titleZh": "设计",
      "name": "design",
      "count": 46
    },
    {
      "title": "Images",
      "titleZh": "图像",
      "name": "images",
      "count": 22
    }
  ],
  "style": "solid",
  "pre": "fas",
  "author": "fontawesome",
  "version": "5.11.0",
  "zhs": [
    "调整",
    "对比",
    "深色",
    "浅色",
    "饱和度",
    "校准",
    "适应",
    "半色"
  ],
  "description": "调整，表示黑与白各一半，也可表示白天黑夜。",
  "comments": []
}